profi_dcp/__init__.py
profi_dcp/dcp_constants.py
profi_dcp/error.py
profi_dcp/profi_dcp.py
profi_dcp/protocol.py
profi_dcp/util.py
profi_dcp/cli/__init__.py
profi_dcp/cli/cli.py
profi_dcp/cli/identify.py
profi_dcp/cli/set_ip.py
profi_dcp/l2socket/__init__.py
profi_dcp/l2socket/l2socket.py
profi_dcp/l2socket/pcap_wrapper.py
profi_dcp/l2socket/winpcap.py
profi_dcp/utils/logging.py
profi_dcp-0.2.0.dist-info/LICENSE
profi_dcp-0.2.0.dist-info/METADATA
profi_dcp-0.2.0.dist-info/WHEEL
profi_dcp-0.2.0.dist-info/entry_points.txt
profi_dcp-0.2.0.dist-info/top_level.txt
profi_dcp-0.2.0.dist-info/RECORD
