Metadata-Version: 2.1
Name: profi-dcp
Version: 0.2.0
Summary: Discover and configure PROFINET devices with the PROFINET Discovery and basic Configuration Protocol (DCP) protocol.
Author-email: Elias Rosch <elias.rosch@festo.com>, Dominic Schlagenhof <dominic.schlagenhof@codewerk.de>, Alexander Riedel <alexander.riedel@codewerk.de>
License: MIT
Project-URL: Documentation, https://festo-research.gitlab.io/electric-automation/festo-edcon
Project-URL: Repository, https://gitlab.com/festo-research/electric-automation/festo-edcon
Project-URL: Changelog, https://gitlab.com/festo-research/electric-automation/festo-edcon/-/blob/main/CHANGELOG.md
Classifier: Development Status :: 5 - Production/Stable
Classifier: Intended Audience :: Developers
Classifier: Intended Audience :: Information Technology
Classifier: Intended Audience :: System Administrators
Classifier: Intended Audience :: Telecommunications Industry
Classifier: Topic :: Software Development :: Libraries
Classifier: Topic :: Software Development :: Libraries :: Python Modules
Classifier: Topic :: System :: Networking
Classifier: Operating System :: Microsoft :: Windows
Classifier: Operating System :: POSIX :: Linux
Classifier: License :: OSI Approved :: MIT License
Classifier: Programming Language :: Python :: 3
Classifier: Programming Language :: Python :: 3.6
Classifier: Programming Language :: Python :: 3.7
Classifier: Programming Language :: Python :: 3.8
Classifier: Programming Language :: Python :: 3.9
Classifier: Programming Language :: Python :: 3.10
Requires-Python: >=3.6
License-File: LICENSE
Requires-Dist: psutil
Requires-Dist: importlib-metadata
Requires-Dist: rich
